[
	{
		"type": 0,
		"class": 0,
	  "id": 0,
		"img": "0.webp",
	  "title": "E云跨境电子商务项目设计UI",
		"info": "",
		"link": "https://www.zcool.com.cn/work/ZMjY1NjAzMzY=.html",
	  "maker": "不就是美工嘛",
	  "time": "2015还是2016年左右"
	},
	{
		"type": 0,
		"class": 0,
	  "id": 1,
		"img": "1.webp",
	  "title": "呼拉圈官网发布",
		"info": "",
		"link": "https://www.zcool.com.cn/work/ZMjg2MzA2ODg=.html",
	  "maker": "不就是美工嘛",
	  "time": "2018-06-26"
	},
	{
		"type": 0,
		"class": 0,
	  "id": 2,
		"img": "2.webp",
	  "title": "ZILLION-INFO WEBSITE DESIGN",
		"info": "",
		"link": "https://www.zcool.com.cn/work/ZMzA2NzI0MDA=.html",
	  "maker": "不就是美工嘛",
	  "time": "2018-08-08"
	},
	{
		"type": 0,
		"class": 0,
	  "id": 3,
		"img": "3.webp",
	  "title": "呼拉圈 微信小程序",
		"info": "",
		"link": "https://www.zcool.com.cn/work/ZMzA5MTAwMTY=.html",
	  "maker": "不就是美工嘛",
	  "time": "2018-10-25"
	},
	{
		"type": 0,
		"class": 0,
	  "id": 4,
		"img": "4.webp",
	  "title": "GCCU logo设计",
		"info": "",
		"link": "https://www.zcool.com.cn/work/ZMzEzOTY4ODg=.html",
	  "maker": "不就是美工嘛",
	  "time": "2018-11-22"
	},
	{
		"type": 0,
		"class": 0,
	  "id": 5,
		"img": "5.webp",
	  "title": "呼拉圈客服系统",
		"info": "",
		"link": "https://www.zcool.com.cn/work/ZMzI3NjUzNTY=.html",
	  "maker": "不就是美工嘛",
	  "time": "2019-03-06"
	},
	{
		"type": 0,
		"class": 0,
	  "id": 6,
		"img": "6.webp",
	  "title": "报告生成系统(web)",
		"info": "",
		"link": "https://www.zcool.com.cn/work/ZMzQzOTQyMzY=.html",
	  "maker": "不就是美工嘛",
	  "time": "2019-03-22"
	},
	{
		"type": 0,
		"class": 0,
	  "id": 7,
		"img": "7.webp",
	  "title": "迪拜华人之家品牌视觉",
		"info": "",
		"link": "https://www.zcool.com.cn/work/ZMzUwMjg4NTY=.html",
	  "maker": "不就是美工嘛",
	  "time": "2019-04-06"
	},
	{
		"type": 0,
		"class": 0,
	  "id": 8,
		"img": "8.webp",
	  "title": "苏璞装饰品牌视觉设计",
		"info": "",
		"link": "https://www.zcool.com.cn/work/ZMzU1NzQyMjg=.html",
	  "maker": "不就是美工嘛",
	  "time": "2019-04-13"
	},
	{
		"type": 0,
		"class": 0,
	  "id": 9,
		"img": "9.webp",
	  "title": "报告生成系统H5",
		"info": "",
		"link": "https://www.zcool.com.cn/work/ZMzYxNjc2MDA=.html",
	  "maker": "不就是美工嘛",
	  "time": "2019-05-23"
	},
	{
		"type": 0,
		"class": 0,
	  "id": 10,
		"img": "10.webp",
	  "title": "线索宝 H5 - V2.0",
		"info": "",
		"link": "https://www.zcool.com.cn/work/ZNDEyNDIwNzY=.html",
	  "maker": "不就是美工嘛",
	  "time": "2019-12-10"
	},
	{
		"type": 1,
		"class": 0,
	  "id": 11,
		"img": "",
	  "title": "[react+ant Design] ProFrom高级表单 格式验证",
		"info": "antD中常用的几种表单格式验证",
		"link": "https://mp.weixin.qq.com/s/rJVHOf6q1sRuIypoKwpvYQ",
	  "time": "2021-06-03"
	},
	{
		"type": 0,
		"class": 0,
	  "id": 12,
		"img": "12.webp",
	  "title": "2020个人简历｜作品整理",
		"info": "",
		"link": "https://www.zcool.com.cn/work/ZNDczNTExOTI=.html",
	  "maker": "不就是美工嘛",
	  "time": "2021-07-15"
	},
	{
		"type": 0,
		"class": 0,
	  "id": 13,
		"img": "13.webp",
	  "title": "呼啦快讯品牌设计",
		"info": "",
		"link": "https://www.zcool.com.cn/work/ZNDczNTExOTI=.html",
	  "maker": "不就是美工嘛",
	  "time": "2021-10-29"
	},
	{
		"type": 0,
		"class": 0,
	  "id": 14,
		"img": "14.webp",
	  "title": "呼叫中心CRM解决方案",
		"info": "",
		"link": "https://www.zcool.com.cn/work/ZNTYzOTA2NjQ=.html",
	  "maker": "不就是美工嘛",
	  "time": "2021-12-13"
	},
	{
		"type": 0,
		"class": 1,
	  "id": 15,
		"img": "15.webp",
	  "title": "移动端设计规范-文字使用规范",
		"info": "",
		"link": "https://mp.weixin.qq.com/s/bfbqADy0ACHXrZHWPmqtOw",
	  "time": "2022-02-07"
	},
	{
		"type": 0,
		"class": 0,
	  "id": 16,
		"img": "16.webp",
	  "title": "Axure 动态面板初使用-实现简单的tab切换页面效果",
		"info": "",
		"link": "https://mp.weixin.qq.com/s/8RvcTh-fvwHYedNUrt-RoQ",
	  "maker": "不就是美工嘛",
	  "time": "2022-03-07"
	},
	{
		"type": 0,
		"class": 0,
	  "id": 17,
		"img": "17.webp",
	  "title": "Axure 动态面板初使用-实现简单的Banner图轮播效果",
		"info": "",
		"link": "https://mp.weixin.qq.com/s/vB92HpsVt4LSF-bFXee4Lg",
	  "maker": "不就是美工嘛",
	  "time": "2022-03-09"
	},
	{
		"type": 1,
		"class": 0,
	  "id": 18,
		"img": "",
	  "title": "关于hover()事件切换的延时处理",
		"info": "关于jquery的hover()事件切换的延时处理，优化弹出隐藏交互动画效果",
		"link": "https://mp.weixin.qq.com/s/0Rw6zObSeD49x1GQc0RSew",
	  "time": "2022-05-28"
	},
	{
		"type": 1,
		"class": 0,
	  "id": 19,
		"img": "",
	  "title": "img标签插入图片下方有空隙，怎么解决？",
		"info": "浏览器中默认的 `img` 标签插入图片下方有空隙，影响页面对齐，那么该怎么快速解决呢？",
		"link": "https://mp.weixin.qq.com/s/7iPQOcaf75eY8MMOYpzwKQ",
	  "time": "2022-06-23"
	},
	{
		"type": 1,
		"class": 0,
	  "id": 20,
		"img": "",
	  "title": "swiper中解决文字不能复制",
		"info": "swiper中有时候想复制其中的文字，但是鼠标去选中文字的时候，slide块会滑走，那该怎么处理了？",
		"link": "https://mp.weixin.qq.com/s/I2bak-NOep6P9Pi02163Tw",
	  "time": "2022-08-26"
	},
	{
		"type": 1,
		"class": 0,
	  "id": 21,
		"img": "",
	  "title": "纯css实现文本内容单行/多行溢出显示省略号",
		"info": "css可以实现单行溢出限制，那能不能实现多行溢出限制呢?",
		"link": "https://mp.weixin.qq.com/s/v-0LUx7OCNQtP4A5Xd4TmA",
	  "time": "2022-08-28"
	},
	{
		"type": 1,
		"class": 0,
	  "id": 22,
		"img": "",
	  "title": "关于让元素垂直居中的几种css写法",
		"info": "前端页面中关于元素垂直居中的几种css写法，面试题中经常潜伏出没~",
		"link": "https://mp.weixin.qq.com/s/uVpREBt6RSiDP7b6zPdiIQ",
	  "time": "2022-09-03"
	},
	{
		"type": 0,
		"class": 1,
	  "id": 24,
		"img": "24.webp",
	  "title": "ps快速绘制长投影效果图标",
		"info": "",
		"link": "https://mp.weixin.qq.com/s/U8DuyNl7gMbekYY-aSDVPg",
	  "time": "2022-09-04"
	},
	{
		"type": 1,
		"class": 0,
	  "id": 25,
		"img": "",
	  "title": "js快速判断设备终端是ios还是android",
		"info": "移动端开发过程中，有些H5页面在设计时，安卓和苹果设备会有一些区别，开发时可以通过js来快速判断",
		"link": "https://mp.weixin.qq.com/s/tsAp12I9Oj7o0oo8Gcnbpw",
	  "time": "2022-12-05"
	},
	{
		"type": 1,
		"class": 0,
	  "id": 26,
		"img": "",
	  "title": "关于css3媒体查询Media的一些用法小结",
		"info": "媒体查询是CSS3中的重要特性，针对不同的设备和屏幕尺寸创建不同的样式。",
		"link": "https://mp.weixin.qq.com/s/alVIOIpe8c84nlVHMVjFlw",
	  "time": "2023-02-17"
	},
	{
		"type": 1,
		"class": 0,
	  "id": 27,
		"img": "",
	  "title": "JSON文件在Vue页面中怎么使用",
		"info": "JSON文件在Vue页面中常见的三种使用方法",
		"link": "https://mp.weixin.qq.com/s/NqikfK5_Zksht0u2ySWNKQ",
	  "time": "2023-02-20"
	},
	{
		"type": 0,
		"class": 0,
	  "id": 28,
		"img": "28.webp",
	  "title": "UI动效如何通过ps放到贴图模板里导出gif效果图",
		"info": "",
		"link": "https://mp.weixin.qq.com/s/4TN1NeSDjhDhaHdCHbsvVA",
	  "maker": "不就是美工嘛",
	  "time": "2023-02-21"
	},
	{
		"type": 1,
		"class": 0,
	  "id": 29,
		"img": "",
	  "title": "js读取上传的文本文件里的内容并在浏览器中渲染显示",
		"info": "上传文本文件，读取文本文件里的内容，并渲染到浏览器中显示出来",
		"link": "https://mp.weixin.qq.com/s/CIqsd4RxUD3jHHyAKleX5A",
	  "time": "2023-03-11"
	},
	{
		"type": 1,
		"class": 0,
	  "id": 30,
		"img": "",
	  "title": "Axios在vue项目中的安装使用以及基本的请求方法",
		"info": "简单介绍了 Axios 在 Vue 项目中怎么去安装、在组件中使用，以及它的一些基本请求方法。",
		"link": "https://mp.weixin.qq.com/s/ZvLpJldTmNRoxPO7JJwDdg",
	  "time": "2023-03-16"
	},
	{
		"type": 1,
		"class": 1,
	  "id": 31,
		"img": "",
	  "title": "用css实现第一个字符串自动生成文字图标",
		"info": "如何用css实现第一个字符串自动生成文字图标效果",
		"link": "https://mp.weixin.qq.com/s/W5rRO4HgDOTqfqyDRtGs2w",
	  "time": "2023-03-17"
	},
	{
		"type": 1,
		"class": 0,
	  "id": 32,
		"img": "",
	  "title": "一般人我都不告诉他的那些css伪选择器",
		"info": "本文介绍一些你不知道，但非常好用的伪选择器，它们可以为网页提供更丰富的样式和交互效果。",
		"link": "https://mp.weixin.qq.com/s/gQVj57hBg_MCvubPNaFMhw",
	  "time": "2023-03-19"
	},
	{
		"type": 1,
		"class": 0,
	  "id": 33,
		"img": "",
	  "title": "你知道html5新增input类型有哪些吗？",
		"info": "Html5 中 input type 类型非常丰富，一些非常好用的类型及示例。",
		"link": "https://mp.weixin.qq.com/s/SIiIgfjLYaSA-HSct3afKA",
	  "time": "2023-03-28"
	},
	{
		"type": 1,
		"class": 0,
	  "id": 34,
		"img": "",
	  "title": "在VUE项目中，使用Axios请求数据时，提示跨域，该怎么解决？",
		"info": "在 VUE 项目中，使用 Axios 请求数据交互时提示跨域，有哪些方式可以去解决？",
		"link": "https://mp.weixin.qq.com/s/0TDQ1Ad5WiztU1QRM_cUVQ",
	  "time": "2023-04-26"
	},
	{
		"type": 1,
		"class": 0,
	  "id": 35,
		"img": "",
	  "title": "CSS Content属性的几种妙用和技巧",
		"info": "你知道 CSS Content 属性能有哪些创意技巧和妙用吗？",
		"link": "https://mp.weixin.qq.com/s/5_lzEYjwC8KUr42uQtHZQQ",
	  "time": "2023-04-28"
	},
	{
		"type": 1,
		"class": 0,
	  "id": 36,
		"img": "",
	  "title": "在React组件中使用JSON数据文件，怎么去读取请求数据呢？",
		"info": "JSON 文件在 React 组件中怎么使用？有几种方法去读取请求 JSON 数据，然后在组件中渲染呢？",
		"link": "https://mp.weixin.qq.com/s/l5atZAzoZRs5u3Z7-ewqVw",
	  "time": "2023-05-04"
	},
	{
		"type": 1,
		"class": 1,
	  "id": 37,
		"img": "",
	  "title": "动态圆点水波纹效果",
		"info": "用 css 实现圆形水波纹效果。",
		"link": "https://mp.weixin.qq.com/s/XcUOW9_-GqdgTlGTMCo0Vg",
	  "time": "2023-05-09"
	},
	{
		"type": 1,
		"class": 0,
	  "id": 38,
		"img": "",
	  "title": "关于学习这件事儿",
		"info": "学而时习之，不亦说乎？",
		"link": "https://mp.weixin.qq.com/s/SPbU5StsebitHx8_t95n-g",
	  "time": "2023-05-10"
	},
	{
		"type": 1,
		"class": 1,
	  "id": 39,
		"img": "",
	  "title": "好看的呼吸灯效果",
		"info": "用纯 CSS 来实现好看的呼吸灯效果。",
		"link": "https://mp.weixin.qq.com/s/muCIhoLC43Ac1qSicdyeIQ",
	  "time": "2023-05-11"
	},
	{
		"type": 1,
		"class": 1,
	  "id": 40,
		"img": "",
	  "title": "动态的毛玻璃背景",
		"info": "用css实现一个有空间感的动态毛玻璃背景效果。",
		"link": "https://mp.weixin.qq.com/s/N0ChsgW1xxC3826hGzs5Ng",
	  "time": "2023-05-16"
	},
	{
		"type": 1,
		"class": 1,
	  "id": 41,
		"img": "",
	  "title": "简约的动态关注按钮",
		"info": "用css实现一个简约的动态关注按钮。",
		"link": "https://mp.weixin.qq.com/s/x8iIC-ik1WqdjiL_3b_Lkw",
	  "time": "2023-05-17"
	},
	{
		"type": 1,
		"class": 1,
	  "id": 42,
		"img": "",
	  "title": "输入框选中交互动效",
		"info": "使用 css 伪选择器配合 required 属性来实现一个简单的输入框的交互效果",
		"link": "https://mp.weixin.qq.com/s/yi-SB_jEC7_fmKyIEXpZLg",
	  "time": "2023-05-23"
	},
	{
		"type": 1,
		"class": 1,
	  "id": 43,
		"img": "",
	  "title": "css loading动画",
		"info": "css3 有很多好玩的属性，可以实现非常多的效果。用css实现一个动态的loading效果。",
		"link": "https://mp.weixin.qq.com/s/0486Fg85lpCXxAVp7KlY2w",
	  "time": "2023-05-24"
	},
	{
		"type": 1,
		"class": 1,
	  "id": 44,
		"img": "",
	  "title": "鼠标悬浮线条动态变化",
		"info": "用css实现鼠标悬浮在文字链接上方时，线条动态变化的交互效果。",
		"link": "https://mp.weixin.qq.com/s/mCZ0sGsqgi3s8ikfPM-zWA",
	  "time": "2023-05-25"
	},
	{
		"type": 1,
		"class": 1,
	  "id": 45,
		"img": "",
	  "title": "按钮文字上下滑动",
		"info": "使用css实现按钮内两个元素上下滑动过渡的交互动画。",
		"link": "https://mp.weixin.qq.com/s/ILVM_qINiKMOoc4IozqDOA",
	  "time": "2023-05-26"
	},
	{
		"type": 1,
		"class": 1,
	  "id": 46,
		"img": "",
	  "title": "多彩变化的按钮",
		"info": "用css实现一个五彩斑斓的变化按钮。",
		"link": "https://mp.weixin.qq.com/s/SKInwEdF6dxpv0sZLkXTkg",
	  "time": "2023-05-29"
	},
	{
		"type": 1,
		"class": 1,
	  "id": 47,
		"img": "",
	  "title": "旋转的太极图",
		"info": "用css画一个旋转的太极图。",
		"link": "https://mp.weixin.qq.com/s/Rl1hmYlaUG31oQQaFveacw",
	  "time": "2023-05-30"
	},
	{
		"type": 0,
		"class": 0,
	  "id": 48,
		"img": "48.webp",
	  "title": "几个好用的 iphone 手机模板贴图",
		"info": "",
		"link": "https://mp.weixin.qq.com/s/TDRlnSZp6cvUEofMmNg_Zg",
	  "maker": "不就是美工嘛",
	  "time": "2023-05-31"
	},
	{
		"type": 1,
		"class": 1,
	  "id": 49,
		"img": "",
	  "title": "新拟态输入框",
		"info": "用 css 模拟新拟态风格输入框被点击时的交互效果。",
		"link": "https://mp.weixin.qq.com/s/z3sdHToTZgflvEKYNOAPTA",
	  "time": "2023-06-02"
	},
	{
		"type": 1,
		"class": 1,
	  "id": 50,
		"img": "",
	  "title": "搜索框小动效",
		"info": "使用css模拟实现搜索图标过渡到输入框的小动效。",
		"link": "https://mp.weixin.qq.com/s/N-4Fo53SOdQe8AoZopksQg",
	  "time": "2023-06-06"
	},
	{
		"type": 1,
		"class": 1,
	  "id": 51,
		"img": "",
	  "title": "简约大方的输入框",
		"info": "一款简约大方的动态输入框，适用于表单提交、账号登录入口。",
		"link": "https://mp.weixin.qq.com/s/rrMVCNIuUNbCIXcQBVZajw",
	  "time": "2023-06-07"
	},
	{
		"type": 1,
		"class": 1,
	  "id": 52,
		"img": "",
	  "title": "一直动的按钮",
		"info": "用css写一个好玩的不停震动的按钮。",
		"link": "https://mp.weixin.qq.com/s/55fUOG9_cw8yRYAjqOwyVw",
	  "time": "2023-06-08"
	},
	{
		"type": 1,
		"class": 1,
	  "id": 53,
		"img": "",
	  "title": "汉堡菜单按钮",
		"info": "用css实现汉堡菜单图标与关闭图标过渡动画交互效果。",
		"link": "https://mp.weixin.qq.com/s/kkzr7UaCCZZSAdRgHJBLMg",
	  "time": "2023-06-09"
	},
	{
		"type": 1,
		"class": 1,
	  "id": 54,
		"img": "",
	  "title": "文字加载动画效果",
		"info": "用css实现多字符模拟加载动画效果。",
		"link": "https://mp.weixin.qq.com/s/EE-IKhrrabwNxnbKSpIquQ",
	  "time": "2023-06-12"
	},
	{
		"type": 1,
		"class": 0,
	  "id": 55,
		"img": "",
	  "title": "mac/windows git ssh 配置多账号多平台",
		"info": "如果你在gitee上有两个账号，github上有两个账号，那么在本地该怎么配置git ssh呢？",
		"link": "https://mp.weixin.qq.com/s/WRB2FOYEzxlP8yz8BCQtOQ",
	  "time": "2023-06-13"
	},
	{
		"type": 1,
		"class": 1,
	  "id": 56,
		"img": "",
	  "title": "好看的聚光灯效果",
		"info": "用css实现一个好看的聚光灯效果。",
		"link": "https://mp.weixin.qq.com/s/uFukJnZJjcJGTSTNZcuTYA",
	  "time": "2023-06-14"
	},
	{
		"type": 1,
		"class": 1,
	  "id": 57,
		"img": "",
	  "title": "弹跳的圆",
		"info": "用css写一个好玩的不停弹跳变形的圆。",
		"link": "https://mp.weixin.qq.com/s/PrnurgVv6_MIfzq2WWzg_A",
	  "time": "2023-06-15"
	},
	{
		"type": 1,
		"class": 1,
	  "id": 58,
		"img": "",
	  "title": "动态的波纹字",
		"info": "用css实现一个不停变化纹理的文字效果。",
		"link": "https://mp.weixin.qq.com/s/SaRcM8NPZLzFCf1pWNVtAg",
	  "time": "2023-06-16"
	},
	{
		"type": 1,
		"class": 1,
	  "id": 59,
		"img": "",
	  "title": "好看的网格阴影文字",
		"info": "用css实现一个好看的网格阴影的文字",
		"link": "https://mp.weixin.qq.com/s/BNPOzsUAp8TPW0GdCOlT3g",
	  "time": "2023-06-17"
	},
	{
		"type": 1,
		"class": 1,
	  "id": 60,
		"img": "",
	  "title": "旋转的金币",
		"info": "一个旋转的金币，适用于游戏网站，会员币等场景。",
		"link": "https://mp.weixin.qq.com/s/GMS-Sc3bRz-u--SP4NcsxQ",
	  "time": "2023-06-20"
	},
	{
		"type": 1,
		"class": 1,
	  "id": 61,
		"img": "",
	  "title": "闪烁的霓虹灯文字",
		"info": "利用 animation 动画实现一个闪烁的霓虹灯文字效果。",
		"link": "https://mp.weixin.qq.com/s/_ozGfr94zv4yKRxjOwfM0w",
	  "time": "2023-06-25"
	},
	{
		"type": 1,
		"class": 1,
	  "id": 62,
		"img": "",
	  "title": "故障字体效果",
		"info": "用css实现一个404故障字体效果。",
		"link": "https://mp.weixin.qq.com/s/zOMaijPXeoO3WZS123iCRw",
	  "time": "2023-06-27"
	},
	{
		"type": 1,
		"class": 1,
	  "id": 63,
		"img": "",
	  "title": "一串乱码",
		"info": "通过css来实现一段不停变化的bug乱码效果。",
		"link": "https://mp.weixin.qq.com/s/6EVrQFALdqDjl4_dAP8ctw",
	  "time": "2023-06-28"
	},
	{
		"type": 1,
		"class": 1,
	  "id": 64,
		"img": "",
	  "title": "加载的圆",
		"info": "由4个圆组成的一个小清新的动态加载动画效果。",
		"link": "https://mp.weixin.qq.com/s/jdHEqLw8TKTxgqkOBZYrYQ",
	  "time": "2023-06-29"
	},
	{
		"type": 1,
		"class": 1,
	  "id": 65,
		"img": "",
	  "title": "鼠标滚动小动效",
		"info": "用css绘制一个鼠标图形，并模拟鼠标的滚轮滚动的小动效。",
		"link": "https://mp.weixin.qq.com/s/myGnWpXjPr_BQc-CbXUhGg",
	  "time": "2023-07-04"
	},
	{
		"type": 1,
		"class": 1,
	  "id": 66,
		"img": "",
	  "title": "输入框交互效果",
		"info": "用 css 实现输入框交互动效。",
		"link": "https://mp.weixin.qq.com/s/_vED_t850MtZJuR7OQRmbA",
	  "time": "2023-07-11"
	},
	{
		"type": 1,
		"class": 1,
	  "id": 67,
		"img": "",
	  "title": "圆点交互按钮",
		"info": "一个有意思的圆点交互文字按钮效果",
		"link": "https://mp.weixin.qq.com/s/cKoNMdiKNX1SjXy-7btjMg",
	  "time": "2023-07-13"
	},
	{
		"type": 0,
		"class": 1,
	  "id": 68,
		"img": "68.webp",
	  "title": "「PS一下」ps中快速抠取透明元素",
		"info": "",
		"link": "https://mp.weixin.qq.com/s/iYK-C4OE55zmXX1gWu10tQ",
	  "time": "2023-07-14"
	},
	{
		"type": 1,
		"class": 1,
	  "id": 69,
		"img": "",
	  "title": "文字上下滑动按钮",
		"info": "一个丝滑好看的按钮。",
		"link": "https://mp.weixin.qq.com/s/9DDplMgrCINMnyIGXo0jdg",
	  "time": "2023-07-15"
	},
	{
		"type": 1,
		"class": 1,
	  "id": 70,
		"img": "",
	  "title": "呼吸灯按钮",
		"info": "一个好玩的呼吸灯效果按钮。",
		"link": "https://mp.weixin.qq.com/s/x_P4Vdw40qKK3oveVYQ91A",
	  "time": "2023-07-16"
	},
	{
		"type": 1,
		"class": 1,
	  "id": 71,
		"img": "",
	  "title": "新拟态按钮",
		"info": "一个好看的新拟态风格的按钮。",
		"link": "https://mp.weixin.qq.com/s/yY591IDvYkT04xsm2LOPlg",
	  "time": "2023-07-18"
	},
	{
		"type": 0,
		"class": 1,
	  "id": 72,
		"img": "72.webp",
	  "title": "「PS一下」制作飞溅溶解字体效果",
		"info": "",
		"link": "https://mp.weixin.qq.com/s/EfDWM6K65uSvlthsSoYTFw",
	  "time": "2023-07-19"
	},
	{
		"type": 0,
		"class": 1,
	  "id": 73,
		"img": "73.webp",
	  "title": "「PS一下」抠图时快速处理多余白边",
		"info": "",
		"link": "https://mp.weixin.qq.com/s/QMNcEennxECJZx4jPG5NuQ",
	  "time": "2023-07-20"
	},
	{
		"type": 1,
		"class": 1,
	  "id": 74,
		"img": "",
	  "title": "好看的开关按钮",
		"info": "用css模拟实现一个好看的开关按钮动效。",
		"link": "https://mp.weixin.qq.com/s/uNKFU5sKK7aerwcHAu28Ww",
	  "time": "2023-07-21"
	},
	{
		"type": 1,
		"class": 1,
	  "id": 75,
		"img": "",
	  "title": "暗黑模式切换开关",
		"info": "用css打造一个切换界面暗黑模式的按钮开关。",
		"link": "https://mp.weixin.qq.com/s/IgHkaV_g_e20NRsUcZARKw",
	  "time": "2023-07-22"
	},
	{
		"type": 1,
		"class": 1,
	  "id": 76,
		"img": "",
	  "title": "提示文字跳起来的输入框",
		"info": "当输入框获取焦点准备输入时，让输入框内提示文字跳起来的交互效果。",
		"link": "https://mp.weixin.qq.com/s/buFQml3xB8VO9Ejmty0SsQ",
	  "time": "2023-07-23"
	},
	{
		"type": 0,
		"class": 1,
	  "id": 77,
		"img": "77.webp",
	  "title": "「PS一下」ps自动混合图层工具快速组合图像",
		"info": "",
		"link": "https://mp.weixin.qq.com/s/DwI1AY98-22VXbQeZC1Qow",
	  "time": "2023-07-24"
	},
	{
		"type": 0,
		"class": 1,
	  "id": 78,
		"img": "78.webp",
	  "title": "sketch绘制毛玻璃图标",
		"info": "",
		"link": "https://mp.weixin.qq.com/s/caRsmNyYuK0Yo1JvEqWSmA",
	  "time": "2023-07-25"
	},
	{
		"type": 0,
		"class": 1,
	  "id": 79,
		"img": "79.webp",
	  "title": "「PS一下」路径模糊快速制作长投影效果",
		"info": "",
		"link": "https://mp.weixin.qq.com/s/eWPKwA-Lmdyh35T2unhPtQ",
	  "time": "2023-07-26"
	},
	{
		"type": 1,
		"class": 1,
	  "id": 80,
		"img": "",
	  "title": "wins98复古按钮",
		"info": "使用  box-shadow 属性模拟绘制 windows98 系统风格按钮。",
		"link": "https://mp.weixin.qq.com/s/58fa_T74LFLENrgdfbrcuw",
	  "time": "2023-07-27"
	},
	{
		"type": 0,
		"class": 1,
	  "id": 81,
		"img": "81.webp",
	  "title": "「PS一下」ps中元素快速进行环形排列",
		"info": "",
		"link": "https://mp.weixin.qq.com/s/SKubOt-B5y9giJ_MfQwqQw",
	  "time": "2023-07-28"
	},
	{
		"type": 0,
		"class": 1,
	  "id": 82,
		"img": "82.webp",
	  "title": "「PS一下」制作液态风格气泡海报",
		"info": "",
		"link": "https://mp.weixin.qq.com/s/hjrIy0jQadA2ppYQGY4vEg",
	  "time": "2023-08-04"
	},
	{
		"type": 1,
		"class": 1,
	  "id": 83,
		"img": "",
	  "title": "音频小动效",
		"info": "用 css3  实现一个好玩的音频小动效。",
		"link": "https://mp.weixin.qq.com/s/zUNSlRPvCHTEFkBN55e1Sg",
	  "time": "2023-08-15"
	},
	{
		"type": 1,
		"class": 1,
	  "id": 84,
		"img": "",
	  "title": "渐变式圆点加载动画",
		"info": "用 css3 模拟一个渐变式圆点加载效果。",
		"link": "https://mp.weixin.qq.com/s/zdNdCOP9xErUgyI-fWUDQg",
	  "time": "2023-08-29"
	},
	{
		"type": 1,
		"class": 1,
	  "id": 85,
		"img": "",
	  "title": "图片懒加载小动效",
		"info": "用 css 实现图片内容懒加载小动效，适用于图片列表懒加载等场景。",
		"link": "https://mp.weixin.qq.com/s/RNJ2bvnvovXBq0ypTgSTYA",
	  "time": "2023-08-31"
	},
	{
		"type": 1,
		"class": 1,
	  "id": 86,
		"img": "",
	  "title": "乱转的指北针",
		"info": "盗墓必备乱转的指北针",
		"link": "https://mp.weixin.qq.com/s/iYl78HDQ8wDXGhR-nGwDow",
	  "time": "2023-09-05"
	},
	{
		"type": 1,
		"class": 1,
	  "id": 87,
		"img": "",
	  "title": "颜色滑动切换按钮",
		"info": "当鼠标悬浮在按钮上方时，按钮背景色从左往右滑动变化",
		"link": "https://mp.weixin.qq.com/s/rDcKsZR2WUbBlSYI3_08SA",
	  "time": "2023-10-13"
	},
	{
		"type": 1,
		"class": 1,
	  "id": 88,
		"img": "",
	  "title": "多弧形加载动画",
		"info": "用纯css实现多双弧线加载动画。",
		"link": "https://mp.weixin.qq.com/s/hTiUfbmUtWRhLUuKVRz1kg",
	  "time": "2023-10-17"
	},
	{
		"type": 1,
		"class": 1,
	  "id": 89,
		"img": "",
	  "title": "丝滑的加载条动画",
		"info": "用css实现一个丝滑的加载条动画效果",
		"link": "https://mp.weixin.qq.com/s/1xVKADRJI19jJqXz2Z4gOg",
	  "time": "2023-10-18"
	},
	{
		"type": 1,
		"class": 1,
	  "id": 90,
		"img": "",
	  "title": "文字下划线条动画按钮",
		"info": "用css实现文字下划线条动画按钮",
		"link": "https://mp.weixin.qq.com/s/JOQaQlMG_Ll9JyJ-cfdlLA",
	  "time": "2023-10-19"
	},
	{
		"type": 1,
		"class": 1,
	  "id": 91,
		"img": "",
	  "title": "旋转的设置按钮",
		"info": "一个会旋转的齿轮设置按钮",
		"link": "https://mp.weixin.qq.com/s/DgClnMLWMtMq_5eVJANniw",
	  "time": "2023-10-20"
	},
	{
		"type": 1,
		"class": 0,
	  "id": 92,
		"img": "",
	  "title": "帮前台小姐姐修电脑时，小姐姐被我一系列操作命令震惊了！",
		"info": "教你如何和前台小姐姐拉近距离",
		"link": "https://mp.weixin.qq.com/s/-blIJsMML-QJG2a_X2nqbg",
	  "time": "2023-10-21"
	},
	{
		"type": 0,
		"class": 1,
	  "id": 93,
		"img": "93.webp",
	  "title": "「PS一下」制作好看的划痕纹理效果",
		"info": "",
		"link": "https://mp.weixin.qq.com/s/gzJbfm4FUgRe50KmDA0Tdg",
	  "time": "2023-10-30"
	},
	{
		"type": 1,
		"class": 1,
	  "id": 94,
		"img": "",
	  "title": "爱心点赞按钮动效",
		"info": "用css实现一个丝滑Q弹的爱心点赞按钮动效",
		"link": "https://mp.weixin.qq.com/s/peoxXsf2I9ZjGLXD8cTy-w",
	  "time": "2023-11-06"
	},
	{
		"type": 1,
		"class": 1,
	  "id": 95,
		"img": "",
	  "title": "暗黑模式切换按钮",
		"info": "一个丝滑的暗黑模式切换按钮。",
		"link": "https://mp.weixin.qq.com/s/mdflV-cNk52AFGq1aTTpQg",
	  "time": "2023-11-27"
	},
	{
		"type": 1,
		"class": 0,
	  "id": 96,
		"img": "",
	  "title": "如何将本地项目代码上传到github代码托管平台上【小白教程】",
		"info": "想把自己写的代码上传到gitee上，该怎么弄？",
		"link": "https://mp.weixin.qq.com/s/DjxG4pO2nNZa5CeOgweAcA",
	  "time": "2023-11-28"
	},
	{
		"type": 1,
		"class": 1,
	  "id": 97,
		"img": "",
	  "title": "旋转的正方体",
		"info": "用css打造一个好看的透明感的旋转正方晶体。",
		"link": "https://mp.weixin.qq.com/s/KNoT-TWQYIn4S01GnFlXNg",
	  "time": "2023-12-20"
	},
	{
		"type": 1,
		"class": 1,
	  "id": 98,
		"img": "",
	  "title": "太极八卦图",
		"info": "css 实现一个动态的太极八卦图",
		"link": "https://mp.weixin.qq.com/s/wkYnmr_HauOZ94af1bBKoQ",
	  "time": "2024-01-03"
	},
	{
		"type": 1,
		"class": 1,
	  "id": 99,
		"img": "",
	  "title": "动态雷达扫描",
		"info": "教你用css实现一个动态的雷达扫描，快学起来吧！",
		"link": "https://mp.weixin.qq.com/s/O6UwpjYAbHuCVjhvFatugQ",
	  "time": "2024-01-11"
	},
	{
		"type": 1,
		"class": 1,
	  "id": 100,
		"img": "",
	  "title": "打字机动画效果",
		"info": "css实现好玩的单行打字机效果，和我一起看看吧~",
		"link": "https://mp.weixin.qq.com/s/L8sxvlDOPfme0Ee7pYZsxQ",
	  "time": "2024-01-12"
	},
	{
		"type": 1,
		"class": 1,
	  "id": 101,
		"img": "",
	  "title": "好看的晶体悬浮效果",
		"info": "教你写出一个炫酷的悬浮晶体效果，让你的网站增光添彩～ hhhh",
		"link": "https://mp.weixin.qq.com/s/oqblKTFCmk0K--_a4FB5pA",
	  "time": "2024-01-15"
	},
	{
		"type": 1,
		"class": 2,
	  "id": 102,
		"img": "",
	  "title": "一个完美的回到顶部按钮",
		"info": "适用于门户网站、个人网站的底部区域，当滚动网站内容到一定高度时，显示“回到顶部”按钮，然后用户点击按钮后，匀速回滚到网站顶部，提高网站用户体验。",
		"link": "https://mp.weixin.qq.com/s/uC0Ixnao_bn9NM0A5LitIQ",
	  "time": "2024-01-16"
	},
	{
		"type": 1,
		"class": 0,
	  "id": 103,
		"img": "",
	  "title": "一直可以正常 git push 代码，突然就不行了，提示端口22错误，访问超时！",
		"info": "github网站正常访问，但是git push代码报错，提示端口22错误，访问超时！怎么搞？",
		"link": "https://mp.weixin.qq.com/s/Rep0iI7xpsm1oQf_-C8z7Q",
	  "time": "2024-01-17"
	},
	{
		"type": 1,
		"class": 1,
	  "id": 104,
		"img": "",
	  "title": "水波纹加载动画",
		"info": "一个丝滑的水波纹加载效果",
		"link": "https://mp.weixin.qq.com/s/M7hV_nYu3xegkQg4Gid-hw",
	  "time": "2024-01-22"
	},
	{
		"type": 1,
		"class": 1,
	  "id": 105,
		"img": "",
	  "title": "卡片翻转效果",
		"info": "利用 css3 属性 backface-visibility 让卡片翻转的过渡动画效果。",
		"link": "https://mp.weixin.qq.com/s/KQY_wBY_Bkn27jtcx6IjVg",
	  "time": "2024-01-24"
	},
	{
		"type": 1,
		"class": 1,
	  "id": 106,
		"img": "",
	  "title": "文字隐身术效果",
		"info": "利用动画属性来模拟文字隐身消失的效果。",
		"link": "https://mp.weixin.qq.com/s/mqWbinx-YE3Ovd4EEZGlhg",
	  "time": "2024-01-29"
	},
	{
		"type": 0,
		"class": 1,
	  "id": 107,
		"img": "107.webp",
	  "title": "怎么绘制出合适又好看的渐变色按钮呢？（新手设计师教程）",
		"info": "",
		"link": "https://mp.weixin.qq.com/s/kOjlyCGgjKlNSxTosjeGzA",
	  "time": "2024-01-31"
	},
	{
		"type": 1,
		"class": 1,
	  "id": 108,
		"img": "",
	  "title": "背景收缩动画按钮",
		"info": "借助 css transition 属性绘制出一个背景收缩交互的一个按钮。",
		"link": "https://mp.weixin.qq.com/s/k500G5246TRfLyOGIr-jig",
	  "time": "2024-02-18"
	},
	{
		"type": 1,
		"class": 1,
	  "id": 109,
		"img": "https://gd-hbimg.huaban.com/028f09de8f7212a9244861dbe632bacfffa2ba9d1d502-8pKnWH",
	  "title": "文字跑马灯按钮",
		"info": "纯css打造一个跑马灯效果的按钮。",
		"link": "https://mp.weixin.qq.com/s/8QbcPfPBC5IoEP4MiV4gpg",
	  "time": "2024-02-21"
	},
	{
		"type": 1,
		"class": 1,
	  "id": 110,
		"img": "https://gd-hbimg.huaban.com/2408d85304c22f671a14fcd3dc7fdfd21625a5177309-LGwU9X",
	  "title": "引导式详情按钮",
		"info": "一个带有图标动效的引导式按钮，适用于阅读详情的引导点击场景。",
		"link": "https://mp.weixin.qq.com/s/-lrAmhvkkZZ_Tig5m5vP8Q",
	  "time": "2024-03-14"
	},
	{
		"type": 1,
		"class": 1,
	  "id": 111,
		"img": "https://gd-hbimg.huaban.com/dbbe1298620f16e029ac0540a20a0201635c9a372004b-z5iCWI",
	  "title": "牛顿摆效果",
		"info": "一个牛顿摆物理效果动效，可以用在 loading 加载动画的需求场景中，提高用户体验感。",
		"link": "https://mp.weixin.qq.com/s/NvpIIeJiqI3i1O_pfYU0_A",
	  "time": "2024-03-29"
	},
	{
		"type": 1,
		"class": 1,
	  "id": 112,
		"img": "https://gd-hbimg.huaban.com/dd3beef17608118598d971b9c13e4448000a009776b3-YQBS7p",
	  "title": "边框动效按钮",
		"info": "交互感比较强的一个动效按钮。",
		"link": "https://mp.weixin.qq.com/s/bctnFKKNbyimpECMEEphWA",
	  "time": "2024-04-01"
	},
	{
		"type": 1,
		"class": 1,
	  "id": 113,
		"img": "https://gd-hbimg.huaban.com/7edc983a80484e9b956fa0f224ae768361e9b8ef381a-mtBjtp",
	  "title": "勾选动效多选框",
		"info": "动效勾选的多选框按钮，适用于注册页中，用户协议勾选时的场景",
		"link": "https://mp.weixin.qq.com/s/TuMTj_GhTtuZ0O0mXSsDiQ",
	  "time": "2024-04-02"
	},
	{
		"type": 1,
		"class": 1,
	  "id": 114,
		"img": "https://gd-hbimg.huaban.com/61d444017e37f8eaca53ecc925bbc440164ebbbf596a-XyczK9",
	  "title": "动态勾选多选框效果",
		"info": "自定义多选框外观，用css实现一个动态勾选多选框按钮，适用于表单中用户勾选多选择项场景",
		"link": "https://mp.weixin.qq.com/s/RgJV5mf88EyPOU4x2pCCvg",
	  "time": "2024-04-07"
	},
	{
		"type": 1,
		"class": 1,
	  "id": 115,
		"img": "https://gd-hbimg.huaban.com/bd4238b9597a8df8ba6ebda184f8e2bd78bca05b7741e-Lz5kKT",
	  "title": "变幻的按钮",
		"info": "一个背景不停变幻的按钮，适用在一些比较年轻、青春风格的网站app中，也可在比较多巴胺风、风格强烈的专题页中使用。",
		"link": "https://mp.weixin.qq.com/s/5L4u-C_6MVFL-Qw-nEOZpA",
	  "time": "2024-04-08"
	},
	{
		"type": 1,
		"class": 1,
	  "id": 116,
		"img": "https://gd-hbimg.huaban.com/a38912a9f492df9cb83fbf82c5ed5ef3b6e945d42b6c8-QFkJtx",
	  "title": "两个圆形加载效果",
		"info": "一款小清新的加载动画，适用于 app 列表加载，页面加载或者弹层内容延迟加载等场景。",
		"link": "https://mp.weixin.qq.com/s/UE41xS9bb3M7xqXKsGMCXA",
	  "time": "2024-04-10"
	},
	{
		"type": 1,
		"class": 1,
	  "id": 117,
		"img": "https://gd-hbimg.huaban.com/5b77caee8abe8c6449a0106267f9ae1b568f61e649f8-128rbu",
	  "title": "移形换位加载动画",
		"info": "移形换位动态加载小动效，适用于 app 列表加载，页面加载或者图片懒加载等场景。",
		"link": "https://mp.weixin.qq.com/s/6U3nCi4hXxQ1l0Sedl9Fvg",
	  "time": "2024-04-12"
	},
	{
		"type": 1,
		"class": 1,
	  "id": 118,
		"img": "https://gd-hbimg.huaban.com/038bc2640e2b3100ea20fcf50499f072951b11116872-xdxGWJ",
	  "title": "圆形背景动效多选框",
		"info": "用 css 实现一个圆形背景动效多选框，适用提醒用户勾选场景，突出多选框选项，可以有效增加用户识别度。",
		"link": "https://mp.weixin.qq.com/s/fGLYrRmxXa0DmG-Ohe6faA",
	  "time": "2024-04-23"
	},
	{
		"type": 1,
		"class": 1,
	  "id": 119,
		"img": "https://gd-hbimg.huaban.com/b657734a9e41ab697891c27903a18eb64d15f51d5179-A2QndO",
	  "title": "加减动态多选框",
		"info": "用 css 实现一个适用树形菜单场景的加减动态多选框。",
		"link": "https://mp.weixin.qq.com/s/H6sBX1aRoDg-1fmKQZKP4w",
	  "time": "2024-04-24"
	},
	{
		"type": 1,
		"class": 1,
	  "id": 120,
		"img": "https://gd-hbimg.huaban.com/1aab43b9e0c1b64c544dfbba1d4052665fac5cdb379da-kVoByy",
	  "title": "水波纹按钮",
		"info": "好看有质感的水波纹按钮，适用大的入口场景，比如 banner 详情入口等，醒目、容易被看到。",
		"link": "https://mp.weixin.qq.com/s/vA33y6SSdh8alyycnwCglA",
	  "time": "2024-04-25"
	},
	{
		"type": 1,
		"class": 1,
	  "id": 121,
		"img": "https://gd-hbimg.huaban.com/16ca43041706a4ddb8618ea8d7bc1c4d6b98289914cf1-yXfpQi",
	  "title": "双开门按钮",
		"info": "一个双开门的按钮，交互效果比较强，但是实现很简单，快学起来吧。",
		"link": "https://mp.weixin.qq.com/s/Y2-QUbiPvl59MvftXz2QGA",
	  "time": "2024-05-14"
	},
	{
		"type": 1,
		"class": 1,
	  "id": 122,
		"img": "https://gd-hbimg.huaban.com/fcfa834d235516df6e23c4826b631a42f808cc2b1877b-exfHA0",
	  "title": "列表块加载动效",
		"info": "css 打造一个极简的列表块加载动效。",
		"link": "https://mp.weixin.qq.com/s/x_um7xRFvzB-WQ_xJT5DRA",
	  "time": "2024-05-16"
	},
	{
		"type": 1,
		"class": 1,
	  "id": 123,
		"img": "https://gd-hbimg.huaban.com/6ddb367d70716e7b22d41c5fbac643f78201184b20f61-imsuyg",
	  "title": "文字流光效果",
		"info": "css实现一个简单丝滑的文字流光效果，适用于页面中的大标题或者引导标题等，起到吸引焦点的作用。",
		"link": "https://mp.weixin.qq.com/s/Qm2BHFVteouu9x0HxVsQkA",
	  "time": "2024-05-20"
	},
	{
		"type": 1,
		"class": 1,
	  "id": 124,
		"img": "https://gd-hbimg.huaban.com/bf48de3bae3bddc4b12910a63fa485977a36bdae7d71-5LS1IG",
	  "title": "拉链式展开按钮",
		"info": "模拟拉链打开效果的按钮，增强页面按钮的交互感。",
		"link": "https://mp.weixin.qq.com/s/VeQaPCrFkej8zTDNUN9Xyg",
	  "time": "2024-05-22"
	},
	{
		"type": 1,
		"class": 1,
	  "id": 125,
		"img": "https://gd-hbimg.huaban.com/1cc2744a576c502de1e9b2f008aec54a28066fb2e9a2-CRdTsy",
	  "title": "跷跷板加载动画",
		"info": "模拟一个跷跷板效果的加载动画，让用户在等待页面加载时更有趣一些。",
		"link": "https://mp.weixin.qq.com/s/R10rtTrbXHFwuHRrIbRfBw",
	  "time": "2024-05-24"
	},
	{
		"type": 1,
		"class": 1,
	  "id": 126,
		"img": "https://gd-hbimg.huaban.com/bcacd7281cc57c643891b4a5813393901d5435f1defa-IfUScE",
	  "title": "多重阴影按钮",
		"info": "用 css 实现一个动效的多重阴影按钮，可用于单独入口的操作按钮。",
		"link": "https://mp.weixin.qq.com/s/HvKlzex6YOJtziSvD2F0-w",
	  "time": "2024-05-29"
	},
	{
		"type": 1,
		"class": 1,
	  "id": 127,
		"img": "https://gd-hbimg.huaban.com/498d1f7f479881b1dc8bccac5ebf0f9fb11cbfaf10e62-PK64tS",
	  "title": "上下线条左右滑动按钮",
		"info": "个性化动态文字按钮，常适用于独立按钮入口，引导用户点击。",
		"link": "https://mp.weixin.qq.com/s/VVB6X9Dg5PCPkv975ok0rQ",
	  "time": "2024-06-04"
	},
	{
		"type": 1,
		"class": 1,
	  "id": 128,
		"img": "https://gd-hbimg.huaban.com/b93581111b23b7449c3b5bc1c8f8d30c7228b43bf5ad-dC5YyU",
	  "title": "圆形金属质感按钮",
		"info": "纯 css 实现一个圆形金属质感按钮，适用于工业机械风格场景。",
		"link": "https://mp.weixin.qq.com/s/cuJUgnxILOGPUJuNOgNFgA",
	  "time": "2024-06-13"
	}
]